mytsoss/__init__.py
mytsoss/bot.py
mytsoss-0.1.2.dist-info/METADATA
mytsoss-0.1.2.dist-info/WHEEL
mytsoss-0.1.2.dist-info/top_level.txt
mytsoss-0.1.2.dist-info/RECORD
